<?xml version="1.0" encoding="utf-8"?>
<odoo>
  <record id="model_custodia_carrier_access_user" model="ir.model.access">
    <field name="name">custodia.carrier.user</field>
    <field name="model_id" ref="model_custodia_carrier"/>
    <field name="group_id" ref="base.group_user"/>
    <field name="perm_read" eval="1"/>
    <field name="perm_write" eval="1"/>
    <field name="perm_create" eval="1"/>
    <field name="perm_unlink" eval="0"/>
  </record>

  <record id="model_custodia_ruta_access_user" model="ir.model.access">
    <field name="name">custodia.ruta.user</field>
    <field name="model_id" ref="model_custodia_ruta"/>
    <field name="group_id" ref="base.group_user"/>
    <field name="perm_read" eval="1"/>
    <field name="perm_write" eval="1"/>
    <field name="perm_create" eval="1"/>
    <field name="perm_unlink" eval="0"/>
  </record>

  <record id="model_custodia_service_access_user" model="ir.model.access">
    <field name="name">custodia.service.user</field>
    <field name="model_id" ref="model_custodia_service"/>
    <field name="group_id" ref="base.group_user"/>
    <field name="perm_read" eval="1"/>
    <field name="perm_write" eval="1"/>
    <field name="perm_create" eval="1"/>
    <field name="perm_unlink" eval="0"/>
  </record>

  <record id="model_custodia_asignacion_access_user" model="ir.model.access">
    <field name="name">custodia.asignacion.user</field>
    <field name="model_id" ref="model_custodia_asignacion"/>
    <field name="group_id" ref="base.group_user"/>
    <field name="perm_read" eval="1"/>
    <field name="perm_write" eval="1"/>
    <field name="perm_create" eval="1"/>
    <field name="perm_unlink" eval="0"/>
  </record>
</odoo>
